{
  "generated_at": "2026-07-24T09:36:02.528Z",
  "range_start": "2026-07-23T09:36:02.528Z",
  "range_end": "2026-07-24T09:36:02.528Z",
  "checked_sources": 10,
  "successful_sources": 5,
  "items": [
    {
      "rank": 1,
      "community": "네이트판",
      "source_title": "경찰이 장윤기 사건 은폐한 이유라는데?",
      "url": "https://pann.nate.com/talk/375533650",
      "published_at": "2026-07-24T09:36:02.528Z",
      "views": 87090,
      "comments": null,
      "recommendations": 386,
      "metrics_visible": true,
      "category": "SOCIETY",
      "topic": "경찰이 장윤기 사건 은폐한 이유라는데?",
      "summary": "경찰이 장윤기 사건 은폐한 이유라는데?",
      "why_trending": "짧은 시간 안에 많은 사람이 확인한 인기글 상위 소재예요.",
      "x_angle": "인기 목록에서 반응이 커진 이유를 짧게 소개",
      "x_hook": "지금 커뮤니티 인기 목록에 오른 이야기: 경찰이 장윤기 사건 은폐한 이유라는데?",
      "fact_check_status": "partial",
      "fact_check_note": "공개 인기 목록의 순위와 확인 가능한 반응 수치를 확인했습니다. 원문 내용은 게시물에서 다시 확인하세요.",
      "risk_level": "low",
      "risk_factors": [],
      "related_sources": [],
      "trend_score": 150.9
    },
    {
      "rank": 2,
      "community": "네이트판",
      "source_title": "내가 뭘 잘못했는지 모르겠어",
      "url": "https://pann.nate.com/talk/375533069",
      "published_at": "2026-07-24T09:36:02.528Z",
      "views": 12908,
      "comments": null,
      "recommendations": 100,
      "metrics_visible": true,
      "category": "CONTENT",
      "topic": "내가 뭘 잘못했는지 모르겠어",
      "summary": "내가 뭘 잘못했는지 모르겠어",
      "why_trending": "짧은 시간 안에 많은 사람이 확인한 인기글 상위 소재예요.",
      "x_angle": "인기 목록에서 반응이 커진 이유를 짧게 소개",
      "x_hook": "지금 커뮤니티 인기 목록에 오른 이야기: 내가 뭘 잘못했는지 모르겠어",
      "fact_check_status": "partial",
      "fact_check_note": "공개 인기 목록의 순위와 확인 가능한 반응 수치를 확인했습니다. 원문 내용은 게시물에서 다시 확인하세요.",
      "risk_level": "low",
      "risk_factors": [],
      "related_sources": [],
      "trend_score": 140.6
    },
    {
      "rank": 3,
      "community": "네이트판",
      "source_title": "선 부탁하는 친척 팩폭했어요",
      "url": "https://pann.nate.com/talk/375533770",
      "published_at": "2026-07-24T09:36:02.528Z",
      "views": 30439,
      "comments": null,
      "recommendations": 78,
      "metrics_visible": true,
      "category": "CONTENT",
      "topic": "선 부탁하는 친척 팩폭했어요",
      "summary": "선 부탁하는 친척 팩폭했어요",
      "why_trending": "짧은 시간 안에 많은 사람이 확인한 인기글 상위 소재예요.",
      "x_angle": "인기 목록에서 반응이 커진 이유를 짧게 소개",
      "x_hook": "지금 커뮤니티 인기 목록에 오른 이야기: 선 부탁하는 친척 팩폭했어요",
      "fact_check_status": "partial",
      "fact_check_note": "공개 인기 목록의 순위와 확인 가능한 반응 수치를 확인했습니다. 원문 내용은 게시물에서 다시 확인하세요.",
      "risk_level": "low",
      "risk_factors": [],
      "related_sources": [],
      "trend_score": 137.9
    },
    {
      "rank": 4,
      "community": "루리웹 베스트",
      "source_title": "아주 평범한 글레이시아 실리콘 피규어.gif",
      "url": "https://bbs.ruliweb.com/best/board/300143/read/76062131?m=humor_only&t=now",
      "published_at": "2026-07-24T09:36:02.528Z",
      "views": null,
      "comments": null,
      "recommendations": null,
      "metrics_visible": false,
      "category": "CONTENT",
      "topic": "아주 평범한 글레이시아 실리콘 피규어.gif",
      "summary": "아주 평범한 글레이시아 실리콘 피규어.gif",
      "why_trending": "해당 커뮤니티 인기 목록 상위에 올라온 소재예요.",
      "x_angle": "인기 목록에서 반응이 커진 이유를 짧게 소개",
      "x_hook": "지금 커뮤니티 인기 목록에 오른 이야기: 아주 평범한 글레이시아 실리콘 피규어.gif (10)",
      "fact_check_status": "partial",
      "fact_check_note": "공개 인기 목록의 상위 노출 순위를 확인했습니다. 세부 반응 수치는 원문에서 다시 확인하세요.",
      "risk_level": "low",
      "risk_factors": [],
      "related_sources": [],
      "trend_score": 114
    },
    {
      "rank": 5,
      "community": "뽐뿌 인기글",
      "source_title": "로랜텍 33W 초고속 보조배터리 60W 케이블 증정 (24,900원/무배)",
      "url": "https://www.ppomppu.co.kr/zboard/view.php?id=ppomppu&no=722424",
      "published_at": "2026-07-24T09:36:02.528Z",
      "views": null,
      "comments": null,
      "recommendations": null,
      "metrics_visible": false,
      "category": "CONTENT",
      "topic": "로랜텍 33W 초고속 보조배터리 60W 케이블 증정 (24,900원/무배)",
      "summary": "로랜텍 33W 초고속 보조배터리 60W 케이블 증정 (24,900원/무배)",
      "why_trending": "해당 커뮤니티 인기 목록 상위에 올라온 소재예요.",
      "x_angle": "인기 목록에서 반응이 커진 이유를 짧게 소개",
      "x_hook": "지금 커뮤니티 인기 목록에 오른 이야기: 로랜텍 33W 초고속 보조배터리 60W 케이블 증정 (24,900원/무배)",
      "fact_check_status": "partial",
      "fact_check_note": "공개 인기 목록의 상위 노출 순위를 확인했습니다. 세부 반응 수치는 원문에서 다시 확인하세요.",
      "risk_level": "low",
      "risk_factors": [],
      "related_sources": [],
      "trend_score": 114
    },
    {
      "rank": 6,
      "community": "MLBPARK 불펜",
      "source_title": "여자끼리하는 소중이 장난 ㄷㄷ.gif",
      "url": "https://mlbpark.donga.com/mp/b.php?b=bullpen&id=202607230117437663&m=view",
      "published_at": "2026-07-24T09:36:02.528Z",
      "views": null,
      "comments": null,
      "recommendations": null,
      "metrics_visible": false,
      "category": "CONTENT",
      "topic": "여자끼리하는 소중이 장난 ㄷㄷ.gif",
      "summary": "여자끼리하는 소중이 장난 ㄷㄷ.gif",
      "why_trending": "해당 커뮤니티 인기 목록 상위에 올라온 소재예요.",
      "x_angle": "인기 목록에서 반응이 커진 이유를 짧게 소개",
      "x_hook": "지금 커뮤니티 인기 목록에 오른 이야기: 여자끼리하는 소중이 장난 ㄷㄷ.gif",
      "fact_check_status": "partial",
      "fact_check_note": "공개 인기 목록의 상위 노출 순위를 확인했습니다. 세부 반응 수치는 원문에서 다시 확인하세요.",
      "risk_level": "low",
      "risk_factors": [],
      "related_sources": [],
      "trend_score": 114
    },
    {
      "rank": 7,
      "community": "루리웹 베스트",
      "source_title": "남자들 남자화장실에서 소변기 쓸때 공감.jpg",
      "url": "https://bbs.ruliweb.com/best/board/300143/read/76062178?m=humor_only&t=now",
      "published_at": "2026-07-24T09:36:02.528Z",
      "views": null,
      "comments": null,
      "recommendations": null,
      "metrics_visible": false,
      "category": "CONTENT",
      "topic": "남자들 남자화장실에서 소변기 쓸때 공감.jpg",
      "summary": "남자들 남자화장실에서 소변기 쓸때 공감.jpg",
      "why_trending": "해당 커뮤니티 인기 목록 상위에 올라온 소재예요.",
      "x_angle": "인기 목록에서 반응이 커진 이유를 짧게 소개",
      "x_hook": "지금 커뮤니티 인기 목록에 오른 이야기: 남자들 남자화장실에서 소변기 쓸때 공감.jpg (18)",
      "fact_check_status": "partial",
      "fact_check_note": "공개 인기 목록의 상위 노출 순위를 확인했습니다. 세부 반응 수치는 원문에서 다시 확인하세요.",
      "risk_level": "low",
      "risk_factors": [],
      "related_sources": [],
      "trend_score": 110
    },
    {
      "rank": 8,
      "community": "루리웹 베스트",
      "source_title": "여자분들 제발 인스타 부계로 전남친 인스타 염탐 그만두세요",
      "url": "https://bbs.ruliweb.com/best/board/300143/read/76062149?m=humor_only&t=now",
      "published_at": "2026-07-24T09:36:02.528Z",
      "views": null,
      "comments": null,
      "recommendations": null,
      "metrics_visible": false,
      "category": "CONTENT",
      "topic": "여자분들 제발 인스타 부계로 전남친 인스타 염탐 그만두세요",
      "summary": "여자분들 제발 인스타 부계로 전남친 인스타 염탐 그만두세요",
      "why_trending": "해당 커뮤니티 인기 목록 상위에 올라온 소재예요.",
      "x_angle": "인기 목록에서 반응이 커진 이유를 짧게 소개",
      "x_hook": "지금 커뮤니티 인기 목록에 오른 이야기: 여자분들 제발 인스타 부계로 전남친 인스타 염탐 그만두세요 (8)",
      "fact_check_status": "partial",
      "fact_check_note": "공개 인기 목록의 상위 노출 순위를 확인했습니다. 세부 반응 수치는 원문에서 다시 확인하세요.",
      "risk_level": "low",
      "risk_factors": [],
      "related_sources": [],
      "trend_score": 106
    }
  ],
  "build": "radar-ranked-v1-20260715",
  "mode": "free-public-scraper",
  "failed_sources": [
    "에펨코리아 포텐",
    "클리앙 추천글",
    "더쿠 HOT",
    "웃긴대학 웃대",
    "인스티즈"
  ],
  "source_diagnostics": [
    {
      "name": "에펨코리아 포텐",
      "url": "https://www.fmkorea.com/best",
      "final_url": "https://www.fmkorea.com/best",
      "elapsed_ms": 594,
      "http_status": 430,
      "content_type": "text/html; charset=UTF-8",
      "status": "http_error",
      "item_count": 0,
      "message": "HTTP 430"
    },
    {
      "name": "디시인사이드 실시간 베스트",
      "url": "https://gall.dcinside.com/board/lists/?id=dcbest",
      "final_url": "https://gall.dcinside.com/board/lists/?id=dcbest",
      "elapsed_ms": 1003,
      "http_status": 200,
      "content_type": "text/html; charset=UTF-8",
      "status": "ok",
      "item_count": 12,
      "html_bytes": 219888,
      "candidate_links": 13,
      "message": "인기 목록 후보를 수집했습니다."
    },
    {
      "name": "루리웹 베스트",
      "url": "https://bbs.ruliweb.com/best",
      "final_url": "https://bbs.ruliweb.com/best",
      "elapsed_ms": 770,
      "http_status": 200,
      "content_type": "text/html; charset=UTF-8",
      "status": "ok",
      "item_count": 12,
      "html_bytes": 175992,
      "candidate_links": 12,
      "message": "인기 목록 후보를 수집했습니다."
    },
    {
      "name": "뽐뿌 인기글",
      "url": "https://www.ppomppu.co.kr/hot.php",
      "final_url": "https://www.ppomppu.co.kr/hot.php",
      "elapsed_ms": 1052,
      "http_status": 200,
      "content_type": "text/html; charset=euc-kr",
      "status": "ok",
      "item_count": 9,
      "html_bytes": 86514,
      "candidate_links": 9,
      "message": "인기 목록 후보를 수집했습니다."
    },
    {
      "name": "클리앙 추천글",
      "url": "https://www.clien.net/service/recommend",
      "final_url": "https://www.clien.net/service/recommend",
      "elapsed_ms": 991,
      "http_status": 410,
      "content_type": "text/html; charset=iso-8859-1",
      "status": "http_error",
      "item_count": 0,
      "message": "HTTP 410"
    },
    {
      "name": "더쿠 HOT",
      "url": "https://theqoo.net/hot",
      "final_url": "https://theqoo.net/hot",
      "elapsed_ms": 261,
      "http_status": 200,
      "content_type": "text/html; charset=UTF-8",
      "status": "blocked_page",
      "item_count": 0,
      "html_bytes": 24770
    },
    {
      "name": "웃긴대학 웃대",
      "url": "https://web.humoruniv.com/board/humor/list.html?table=pds",
      "final_url": "https://web.humoruniv.com/board/humor/list.html?table=pds",
      "elapsed_ms": 869,
      "http_status": 200,
      "content_type": "text/html",
      "status": "no_candidates",
      "item_count": 0,
      "html_bytes": 91544,
      "candidate_links": 0,
      "message": "사이트별 URL 또는 지표 규칙을 통과하지 못했습니다."
    },
    {
      "name": "MLBPARK 불펜",
      "url": "https://mlbpark.donga.com/mp/best.php?b=bullpen&m=view",
      "final_url": "https://mlbpark.donga.com/mp/best.php?b=bullpen&m=view",
      "elapsed_ms": 2378,
      "http_status": 200,
      "content_type": "text/html; charset=UTF-8",
      "status": "ok",
      "item_count": 12,
      "html_bytes": 84258,
      "candidate_links": 12,
      "message": "인기 목록 후보를 수집했습니다."
    },
    {
      "name": "인스티즈",
      "url": "https://www.instiz.net/pt",
      "final_url": "https://www.instiz.net/pt",
      "elapsed_ms": 494,
      "http_status": 200,
      "content_type": "text/html; charset=UTF-8",
      "status": "no_candidates",
      "item_count": 0,
      "html_bytes": 100409,
      "candidate_links": 0,
      "message": "사이트별 URL 또는 지표 규칙을 통과하지 못했습니다."
    },
    {
      "name": "네이트판",
      "url": "https://pann.nate.com/talk/ranking",
      "final_url": "https://pann.nate.com/talk/ranking",
      "elapsed_ms": 1497,
      "http_status": 200,
      "content_type": "text/html; charset=utf-8",
      "status": "ok",
      "item_count": 12,
      "html_bytes": 84351,
      "candidate_links": 12,
      "message": "인기 목록 후보를 수집했습니다."
    }
  ]
}
